config_backend/__init__.py
gailbot/__init__.py
gailbot/api.py
gailbot/configs/__init__.py
gailbot/configs/confs/__init__.py
gailbot/configs/confs/paths.py
gailbot/configs/interfaces/__init__.py
gailbot/configs/interfaces/config/ws_config.py
gailbot/configs/interfaces/core/engines/google.py
gailbot/configs/interfaces/core/engines/watson.py
gailbot/configs/interfaces/core/engines/whisper.py
gailbot/configs/interfaces/core/setting/defaults.py
gailbot/configs/interfaces/core/util/logger.py
gailbot/configs/interfaces/plugin/__init__.py
gailbot/configs/interfaces/plugin/pluginsuite.py
gailbot/configs/interfaces/plugin/validstructure.py
gailbot/configs/interfaces/services/__init__.py
gailbot/configs/interfaces/services/service.py
gailbot/core/__init__.py
gailbot/core/engines/__init__.py
gailbot/core/engines/engine.py
gailbot/core/engines/engineManager.py
gailbot/core/engines/exception.py
gailbot/core/engines/google/__init__.py
gailbot/core/engines/google/core.py
gailbot/core/engines/google/google.py
gailbot/core/engines/watson/__init__.py
gailbot/core/engines/watson/am.py
gailbot/core/engines/watson/codes.py
gailbot/core/engines/watson/core.py
gailbot/core/engines/watson/lm.py
gailbot/core/engines/watson/recognition_results.py
gailbot/core/engines/watson/recognize_callback.py
gailbot/core/engines/watson/watson.py
gailbot/core/engines/whisperEngine/__init__.py
gailbot/core/engines/whisperEngine/core.py
gailbot/core/engines/whisperEngine/parsers.py
gailbot/core/engines/whisperEngine/whisperEngine.py
gailbot/core/engines/whisperEngine/diarization/__init__.py
gailbot/core/engines/whisperEngine/diarization/diarize.py
gailbot/core/engines/whisperEngine/diarization/utils.py
gailbot/core/engines/whisperEngine/whisperTimestamped/__init__.py
gailbot/core/engines/whisperEngine/whisperTimestamped/alignment.py
gailbot/core/engines/whisperEngine/whisperTimestamped/transcribe.py
gailbot/core/engines/whisperEngine/whisperTimestamped/transcribe_efficient.py
GailBot_Testing_Suite-0.1a8.dist-info/LICENSE
GailBot_Testing_Suite-0.1a8.dist-info/METADATA
GailBot_Testing_Suite-0.1a8.dist-info/WHEEL
GailBot_Testing_Suite-0.1a8.dist-info/top_level.txt
GailBot_Testing_Suite-0.1a8.dist-info/RECORD
