Metadata-Version: 2.1
Name: GailBot-Testing-Suite
Version: 0.1a8
Summary: Testing suite for GailBot software
Author-email: "Jason Y. Wu" <jason.wu@tufts.edu>
Maintainer-email: Human Interaction Lab - Tufts University <hilab-dev@elist.tufts.edu>
License: MIT License        
Project-URL: homepage, https://github.com/mumair01/GailBot
Project-URL: source, https://github.com/mumair01/GailBot
Project-URL: tracker, https://github.com/mumair01/GailBot/issues
Classifier: Intended Audience :: Science/Research
Classifier: Programming Language :: Python
Classifier: Programming Language :: Python :: 3
Classifier: Programming Language :: Python :: 3.8
Classifier: Topic :: Scientific/Engineering
Classifier: Operating System :: MacOS
Requires-Python: >=3.10
License-File: LICENSE
Requires-Dist: d
Provides-Extra: dev
Requires-Dist: pytest ; extra == 'dev'
Requires-Dist: pytest-cov ; extra == 'dev'
Requires-Dist: pytest-timeout ; extra == 'dev'
Requires-Dist: pytest-xdist ; extra == 'dev'
Requires-Dist: ipython ; extra == 'dev'
